LICENSE
MANIFEST.in
README.rst
RawFileReaderLicense.rst
requirements.txt
setup.py
dimspy/__init__.py
dimspy/__main__.py
dimspy/metadata.py
dimspy/tools.py
dimspy.egg-info/PKG-INFO
dimspy.egg-info/SOURCES.txt
dimspy.egg-info/dependency_links.txt
dimspy.egg-info/entry_points.txt
dimspy.egg-info/requires.txt
dimspy.egg-info/top_level.txt
dimspy/models/__init__.py
dimspy/models/peak_matrix.py
dimspy/models/peaklist.py
dimspy/models/peaklist_metadata.py
dimspy/models/peaklist_tags.py
dimspy/portals/__init__.py
dimspy/portals/hdf5_portal.py
dimspy/portals/mzml_portal.py
dimspy/portals/paths.py
dimspy/portals/thermo_raw_portal.py
dimspy/portals/txt_portal.py
dimspy/portals/ThermoRawFileReader_3_0_41/Libraries/ThermoFisher.CommonCore.BackgroundSubtraction.XML
dimspy/portals/ThermoRawFileReader_3_0_41/Libraries/ThermoFisher.CommonCore.BackgroundSubtraction.dll
dimspy/portals/ThermoRawFileReader_3_0_41/Libraries/ThermoFisher.CommonCore.Data.XML
dimspy/portals/ThermoRawFileReader_3_0_41/Libraries/ThermoFisher.CommonCore.Data.dll
dimspy/portals/ThermoRawFileReader_3_0_41/Libraries/ThermoFisher.CommonCore.MassPrecisionEstimator.XML
dimspy/portals/ThermoRawFileReader_3_0_41/Libraries/ThermoFisher.CommonCore.MassPrecisionEstimator.dll
dimspy/portals/ThermoRawFileReader_3_0_41/Libraries/ThermoFisher.CommonCore.RawFileReader.XML
dimspy/portals/ThermoRawFileReader_3_0_41/Libraries/ThermoFisher.CommonCore.RawFileReader.dll
dimspy/portals/ThermoRawFileReader_3_0_41/License/RawFileRdr_License_Agreement_RevA.doc
dimspy/process/__init__.py
dimspy/process/peak_alignment.py
dimspy/process/peak_filters.py
dimspy/process/replicate_processing.py
examples/examples.py
examples/run.bat
examples/run.sh
tests/__init__.py
tests/test_hdf5_portal.py
tests/test_metadata.py
tests/test_mzml_portal.py
tests/test_paths_portal.py
tests/test_peak_alignment.py
tests/test_peak_filters.py
tests/test_peak_matrix.py
tests/test_peaklist.py
tests/test_peaklist_metadata.py
tests/test_peaklist_tags.py
tests/test_replicate_processing.py
tests/test_suite_models.py
tests/test_suite_portals.py
tests/test_suite_process.py
tests/test_suite_tools.py
tests/test_thermo_raw_portal.py
tests/test_tools.py
