Metadata-Version: 1.2
Name: dimspy
Version: 2.0.0
Summary: Python package for processing of direct-infusion mass spectrometry-based metabolomics and lipidomics data
Home-page: https://github.com/computational-metabolomics/dimspy
Author: Ralf Weber, Albert Zhou
Author-email: r.j.weber@bham.ac.uk, j.zhou.3@bham.ac.uk 
License: GPLv3
Project-URL: Documentation, https://dimspy.readthedocs.io/en/latest/
Project-URL: Changelog, https://dimspy.readthedocs.io/en/latest/changelog.html
Project-URL: Bug Tracker, https://github.com/computational-metabolomics/dimspy/issues
Keywords: Metabolomics,Lipidomics,Mass spectrometry,Data Processing,Direct-Infusion Mass Spectrometry
Platform: Windows, UNIX
Classifier: Programming Language :: Python :: 3
Classifier: Programming Language :: Python :: 3.7
Classifier: Topic :: Scientific/Engineering :: Bio-Informatics
Classifier: Topic :: Scientific/Engineering :: Chemistry
Classifier: Topic :: Utilities
Classifier: License :: OSI Approved :: GNU General Public License v3 (GPLv3)
Classifier: Operating System :: OS Independent
Requires-Python: >=3.7
